[
    {
        "description": "Zipangu: Honnou-ji, Ranmaru boss theme",
        "filename": "InsideHonnouji",
        "mark": "Honnouji",
        "metadata": {
            "albumArtist": "Wizet",
            "artist": "StudioEIM",
            "title": "Inside Honnouji",
            "year": "2012"
        },
        "source": {
            "client": "JMS",
            "date": "2012-07-11",
            "structure": "BgmJp3",
            "version": "3.00"
        },
        "youtube": "WK-aE_3PF8g"
    },
    {
        "description": "Takigawa Kazumasu boss theme, Sengoku quest",
        "filename": "SengokuBoss",
        "mark": "Honnouji",
        "metadata": {
            "albumArtist": "Wizet",
            "artist": "StudioEIM",
            "title": "Sengoku Boss",
            "year": "2012"
        },
        "source": {
            "client": "JMS",
            "date": "2012-07-11",
            "structure": "BgmJp3",
            "version": "3.00"
        },
        "youtube": "OKufViI86Tk"
    }
]