[
    {
        "description": "Mesoranger dance event",
        "filename": "rhythmBgm1",
        "mark": "mRhythm",
        "metadata": {
            "albumArtist": "Wizet",
            "artist": "StudioEIM",
            "title": "Rhythm",
            "year": "2013"
        },
        "source": {
            "client": "KMST",
            "date": "2013-04-18",
            "structure": "BgmEvent2",
            "version": "1.2.476"
        },
        "youtube": "siOIcI8Fa3A"
    },
    {
        "description": "Mesoranger dance event",
        "filename": "rhythmBgm2",
        "mark": "mRhythm",
        "metadata": {
            "albumArtist": "Wizet",
            "artist": "StudioEIM",
            "title": "Rhythm 2",
            "year": "2013"
        },
        "source": {
            "client": "KMST",
            "date": "2013-06-27",
            "structure": "BgmEvent2",
            "version": "1.2.481"
        },
        "youtube": "iFUeN8brMbo"
    },
    {
        "description": "Mesoranger dance event (winter)",
        "filename": "santaBeats",
        "mark": "mRhythm",
        "metadata": {
            "albumArtist": "Wizet",
            "artist": "StudioEIM",
            "title": "Santa Beats",
            "year": "2013"
        },
        "source": {
            "client": "KMST",
            "date": "2013-11-27",
            "structure": "BgmEvent2",
            "version": "1.2.492"
        },
        "youtube": "6AY9MkUSc9s"
    },
    {
        "description": "Mesoranger dance event (winter)",
        "filename": "santaRocks",
        "mark": "mRhythm",
        "metadata": {
            "albumArtist": "Wizet",
            "artist": "StudioEIM",
            "title": "Santa Rocks",
            "year": "2013"
        },
        "source": {
            "client": "KMST",
            "date": "2013-11-27",
            "structure": "BgmEvent2",
            "version": "1.2.492"
        },
        "youtube": "t-Ra1k_Dk2k"
    }
]