[
    {
        "description": "Stellar Detectives theme",
        "filename": "MD_AcornDetective_AR",
        "mark": "PL_MapleDetective",
        "metadata": {
            "albumArtist": "NECORD",
            "artist": "ASTERIA",
            "title": "Stellar Detectives",
            "titleAlt": "Maple Detective: Acorn Detective AR",
            "year": "2016"
        },
        "source": {
            "client": "CMST",
            "date": "2016-04-29",
            "structure": "BgmPL",
            "version": "1.15"
        },
        "youtube": "3SEaLivUIg4"
    },
    {
        "description": "Stellar Detectives theme (instrumental)",
        "filename": "MD_AcornDetective_MR",
        "mark": "PL_MapleDetective",
        "metadata": {
            "albumArtist": "NECORD",
            "artist": "ASTERIA",
            "title": "Stellar Detectives -instrumental-",
            "titleAlt": "Maple Detective: Acorn Detective MR",
            "year": "2016"
        },
        "source": {
            "client": "CMST",
            "date": "2016-04-29",
            "structure": "BgmPL",
            "version": "1.15"
        },
        "youtube": "s9H92aOgW1U"
    },
    {
        "description": "Stellar Detectives: Hyperspace Cube",
        "filename": "MD_InvadeOperation",
        "mark": "PL_MapleDetective",
        "metadata": {
            "albumArtist": "NECORD",
            "artist": "ASTERIA",
            "title": "Mission: Invasion",
            "titleAlt": "Maple Detective: Invade Operation",
            "year": "2016"
        },
        "source": {
            "client": "CMST",
            "date": "2016-04-29",
            "structure": "BgmPL",
            "version": "1.15"
        },
        "youtube": "pCXDV2_wUY4"
    }
]